FastHareComposite/FastHareComposite.py
FastHareComposite/HamGraphSimple.py
FastHareComposite/__init__.py
FastHareComposite-0.3.5.dist-info/LICENSE
FastHareComposite-0.3.5.dist-info/METADATA
FastHareComposite-0.3.5.dist-info/WHEEL
FastHareComposite-0.3.5.dist-info/top_level.txt
FastHareComposite-0.3.5.dist-info/RECORD
