Metadata-Version: 2.1
Name: FastHareComposite
Version: 0.3.5
Summary: A composite for using FastHare reduction with the samplers from D-Wave Ocean SDK
Home-page: https://github.com/thang-dinh/FastHare
Author: Thang N. Dinh
Author-email: thangdn@gmail.com
Classifier: Programming Language :: Python :: 3
Classifier: License :: OSI Approved :: MIT License
Classifier: Operating System :: OS Independent
Requires-Python: >=3.10
License-File: LICENSE
Requires-Dist: dimod
Requires-Dist: fasthare
Requires-Dist: networkx
